minimapi/__init__.py
minimapi/minimapi.py
minimapi/sanitizer.py
minimapi/auth_modules/bearer.py
minimapi/auth_modules/ecdsa.py
minimapi/auth_modules/jwt.py
minimapi/auth_modules/none.py
minimapi/data_types/date.py
minimapi/data_types/email.py
minimapi/data_types/number.py
minimapi/data_types/password.py
minimapi/data_types/pbkdf2.py
minimapi/data_types/sha256.py
minimapi/data_types/text.py
minimapi/data_types/totp.py
minimapi/data_types/url.py
minimapi/database_connectors/pysondb.py
minimapi-0.0.6.dist-info/METADATA
minimapi-0.0.6.dist-info/WHEEL
minimapi-0.0.6.dist-info/licenses/LICENSE
minimapi-0.0.6.dist-info/RECORD
