Metadata-Version: 2.1
Name: minimapi
Version: 0.0.6
Summary: Easy and simple REST API from model
Project-URL: Homepage, https://github.com/minimapi/minimapi
Project-URL: Bug Tracker, https://github.com/minimapi/minimapi/issues
License-File: LICENSE
Classifier: License :: OSI Approved :: MIT License
Classifier: Programming Language :: Python :: 3
Classifier: Topic :: Internet :: WWW/HTTP
Requires-Python: >=3.7
Requires-Dist: ecdsa>=0.18.0
Requires-Dist: flask>=2.2.0
Requires-Dist: pyjwt>=2.6.0
Requires-Dist: pyotp>=2.7.0
Requires-Dist: pysondb>=1.6.7
